pipbar/__init__.py
pipbar/installer.py
pipbar-0.1.1.dist-info/METADATA
pipbar-0.1.1.dist-info/WHEEL
pipbar-0.1.1.dist-info/top_level.txt
pipbar-0.1.1.dist-info/RECORD
