Metadata-Version: 2.1
Name: pipbar
Version: 0.1.1
Summary: A progress bar tool for pip installations
Home-page: https://github.com/Jiyath5516F/pip-bar
Author: Jiyath Khan
Author-email: jiyathf@gmail.com
Classifier: Programming Language :: Python :: 3
Classifier: License :: OSI Approved :: MIT License
Classifier: Operating System :: OS Independent
Requires-Python: >=3.6
Requires-Dist: rich
